torchbase/__init__.py
torchbase/session.py
torchbase/utils/__init__.py
torchbase/utils/data.py
torchbase/utils/logger.py
torchbase/utils/metrics.py
torchbase/utils/metrics_instances.py
torchbase/utils/networks.py
torchbase/utils/session.py
torchbase-0.1.3.dist-info/LICENSE
torchbase-0.1.3.dist-info/METADATA
torchbase-0.1.3.dist-info/WHEEL
torchbase-0.1.3.dist-info/RECORD
