Metadata-Version: 2.3
Name: torchbase
Version: 0.1.3
Summary: A minimalist base for ML projects in PyTorch
License: Apache-2.0
Author: Sohrab Ferdowsi
Author-email: sohrab.ferdowsi@gmail.com
Requires-Python: >=3.10
Classifier: License :: OSI Approved :: Apache Software License
Classifier: Programming Language :: Python :: 3
Classifier: Programming Language :: Python :: 3.10
Classifier: Programming Language :: Python :: 3.11
Classifier: Programming Language :: Python :: 3.12
Classifier: Programming Language :: Python :: 3.13
Requires-Dist: datasets
Requires-Dist: numpy
Requires-Dist: scikit-learn
Requires-Dist: tensorboard
Requires-Dist: torch
